llmrepo/__init__.py
llmrepo/tools/__init__.py
llmrepo-0.1.0.dist-info/METADATA
llmrepo-0.1.0.dist-info/WHEEL
llmrepo-0.1.0.dist-info/RECORD
