Metadata-Version: 2.4
Name: llmrepo
Version: 0.1.0
Summary: A package for building and managing tools for Large Language Models
Project-URL: Homepage, https://github.com/rhbuckley/llmrepo
Project-URL: Source, https://github.com/rhbuckley/llmrepo
Project-URL: Bug Tracker, https://github.com/rhbuckley/llmrepo/issues
Author-email: Richard Buckley <rhbuckley@pm.me>
Classifier: Development Status :: 4 - Beta
Classifier: Intended Audience :: Developers
Classifier: License :: OSI Approved :: MIT License
Classifier: Programming Language :: Python :: 3
Classifier: Programming Language :: Python :: 3 :: Only
Classifier: Programming Language :: Python :: 3.9
Classifier: Programming Language :: Python :: 3.10
Classifier: Programming Language :: Python :: 3.11
Classifier: Programming Language :: Python :: 3.12
Classifier: Programming Language :: Python :: 3.13
Classifier: Topic :: Software Development :: Build Tools
Requires-Python: >=3.8
Requires-Dist: pydantic>=2.0.0
Provides-Extra: dev
Requires-Dist: check-manifest; extra == 'dev'
Provides-Extra: test
Requires-Dist: pytest-asyncio>=0.22.0; extra == 'test'
Requires-Dist: pytest>=8.0.0; extra == 'test'
